{"licenses": [{"name": "", "id": 0, "url": ""}], "info": {"description": "Heron baseline pre-annotations for eaf", "date_created": "2026-05-02T22:46:40.525588"}, "categories": [{"id": 1, "name": "Document Index", "supercategory": ""}, {"id": 2, "name": "List-item", "supercategory": ""}, {"id": 3, "name": "Footnote", "supercategory": ""}, {"id": 4, "name": "Checkbox-selected", "supercategory": ""}, {"id": 5, "name": "Page-header", "supercategory": ""}, {"id": 6, "name": "Checkbox-unselected", "supercategory": ""}, {"id": 7, "name": "Code", "supercategory": ""}, {"id": 8, "name": "Table", "supercategory": ""}, {"id": 9, "name": "Text", "supercategory": ""}, {"id": 10, "name": "Section-header", "supercategory": ""}, {"id": 11, "name": "Formula", "supercategory": ""}, {"id": 12, "name": "Picture", "supercategory": ""}, {"id": 13, "name": "Key-value-region", "supercategory": ""}, {"id": 14, "name": "Caption", "supercategory": ""}, {"id": 15, "name": "Title", "supercategory": ""}, {"id": 16, "name": "Form", "supercategory": ""}, {"id": 17, "name": "Page-footer", "supercategory": ""}], "images": [{"id": 1, "width": 2550, "height": 3300, "file_name": "pagina-001.png"}, {"id": 2, "width": 2550, "height": 3300, "file_name": "pagina-002.png"}, {"id": 3, "width": 2550, "height": 3300, "file_name": "pagina-003.png"}, {"id": 4, "width": 2550, "height": 3300, "file_name": "pagina-004.png"}, {"id": 5, "width": 2550, "height": 3300, "file_name": "pagina-005.png"}], "annotations": [{"id": 1, "image_id": 1, "category_id": 8, "bbox": [400.71, 1525.54, 1893.47, 662.24], "area": 1253938.15, "iscrowd": 0, "segmentation": [], "score": 0.9921, "attributes": {"occluded": false, "rotation": 0.0}}, {"id": 2, "image_id": 1, "category_id": 8, "bbox": [401.51, 930.28, 1892.64, 443.0], "area": 838442.81, "iscrowd": 0, "segmentation": [], "score": 0.9913, "attributes": {"occluded": false, "rotation": 0.0}}, {"id": 3, "image_id": 1, "category_id": 8, "bbox": [401.98, 2317.78, 1892.61, 484.71], "area": 917371.83, "iscrowd": 0, "segmentation": [], "score": 0.9898, "attributes": {"occluded": false, "rotation": 0.0}}, {"id": 4, "image_id": 1, "category_id": 17, "bbox": [1982.03, 3040.12, 304.01, 39.85], "area": 12115.24, "iscrowd": 0, "segmentation": [], "score": 0.953, "attributes": {"occluded": false, "rotation": 0.0}}, {"id": 5, "image_id": 1, "category_id": 10, "bbox": [235.34, 695.79, 1023.7, 41.11], "area": 42088.26, "iscrowd": 0, "segmentation": [], "score": 0.9351, "attributes": {"occluded": false, "rotation": 0.0}}, {"id": 6, "image_id": 1, "category_id": 10, "bbox": [293.25, 1446.76, 801.11, 33.65], "area": 26959.11, "iscrowd": 0, "segmentation": [], "score": 0.9249, "attributes": {"occluded": false, "rotation": 0.0}}, {"id": 7, "image_id": 1, "category_id": 10, "bbox": [293.6, 2241.35, 807.71, 33.37], "area": 26956.78, "iscrowd": 0, "segmentation": [], "score": 0.9226, "attributes": {"occluded": false, "rotation": 0.0}}, {"id": 8, "image_id": 1, "category_id": 10, "bbox": [293.41, 853.63, 584.22, 39.69], "area": 23189.26, "iscrowd": 0, "segmentation": [], "score": 0.914, "attributes": {"occluded": false, "rotation": 0.0}}, {"id": 9, "image_id": 1, "category_id": 10, "bbox": [812.39, 289.83, 921.12, 40.54], "area": 37340.83, "iscrowd": 0, "segmentation": [], "score": 0.854, "attributes": {"occluded": false, "rotation": 0.0}}, {"id": 10, "image_id": 1, "category_id": 10, "bbox": [372.01, 410.75, 1802.19, 34.51], "area": 62201.6, "iscrowd": 0, "segmentation": [], "score": 0.5577, "attributes": {"occluded": false, "rotation": 0.0}}, {"id": 11, "image_id": 1, "category_id": 9, "bbox": [1347.82, 484.98, 246.72, 31.56], "area": 7787.16, "iscrowd": 0, "segmentation": [], "score": 0.7969, "attributes": {"occluded": false, "rotation": 0.0}}, {"id": 12, "image_id": 1, "category_id": 9, "bbox": [952.81, 484.17, 380.13, 32.06], "area": 12186.92, "iscrowd": 0, "segmentation": [], "score": 0.7754, "attributes": {"occluded": false, "rotation": 0.0}}, {"id": 13, "image_id": 1, "category_id": 9, "bbox": [372.01, 410.75, 1802.19, 34.51], "area": 62201.6, "iscrowd": 0, "segmentation": [], "score": 0.6228, "attributes": {"occluded": false, "rotation": 0.0}}, {"id": 14, "image_id": 1, "category_id": 13, "bbox": [952.04, 484.05, 641.99, 32.27], "area": 20718.81, "iscrowd": 0, "segmentation": [], "score": 0.7366, "attributes": {"occluded": false, "rotation": 0.0}}, {"id": 15, "image_id": 2, "category_id": 9, "bbox": [388.39, 1915.11, 1938.07, 591.85], "area": 1147047.71, "iscrowd": 0, "segmentation": [], "score": 0.9904, "attributes": {"occluded": false, "rotation": 0.0}}, {"id": 16, "image_id": 2, "category_id": 9, "bbox": [388.98, 569.56, 1935.54, 373.0], "area": 721961.5, "iscrowd": 0, "segmentation": [], "score": 0.9893, "attributes": {"occluded": false, "rotation": 0.0}}, {"id": 17, "image_id": 2, "category_id": 9, "bbox": [388.72, 981.45, 1935.63, 427.44], "area": 827372.48, "iscrowd": 0, "segmentation": [], "score": 0.9891, "attributes": {"occluded": false, "rotation": 0.0}}, {"id": 18, "image_id": 2, "category_id": 9, "bbox": [388.67, 1448.39, 1934.36, 427.86], "area": 827627.84, "iscrowd": 0, "segmentation": [], "score": 0.9888, "attributes": {"occluded": false, "rotation": 0.0}}, {"id": 19, "image_id": 2, "category_id": 9, "bbox": [387.94, 321.13, 1938.79, 209.39], "area": 405959.42, "iscrowd": 0, "segmentation": [], "score": 0.9859, "attributes": {"occluded": false, "rotation": 0.0}}, {"id": 20, "image_id": 2, "category_id": 9, "bbox": [388.55, 2545.29, 1939.91, 154.88], "area": 300446.62, "iscrowd": 0, "segmentation": [], "score": 0.982, "attributes": {"occluded": false, "rotation": 0.0}}, {"id": 21, "image_id": 2, "category_id": 9, "bbox": [388.52, 2822.33, 916.79, 44.52], "area": 40819.71, "iscrowd": 0, "segmentation": [], "score": 0.912, "attributes": {"occluded": false, "rotation": 0.0}}, {"id": 22, "image_id": 2, "category_id": 10, "bbox": [294.1, 236.16, 632.05, 46.13], "area": 29157.31, "iscrowd": 0, "segmentation": [], "score": 0.9078, "attributes": {"occluded": false, "rotation": 0.0}}, {"id": 23, "image_id": 2, "category_id": 10, "bbox": [294.46, 2738.49, 464.46, 45.34], "area": 21059.92, "iscrowd": 0, "segmentation": [], "score": 0.9009, "attributes": {"occluded": false, "rotation": 0.0}}, {"id": 24, "image_id": 2, "category_id": 17, "bbox": [1982.22, 3038.4, 312.01, 41.58], "area": 12972.22, "iscrowd": 0, "segmentation": [], "score": 0.9024, "attributes": {"occluded": false, "rotation": 0.0}}, {"id": 25, "image_id": 3, "category_id": 9, "bbox": [388.21, 1039.97, 1939.82, 321.39], "area": 623443.87, "iscrowd": 0, "segmentation": [], "score": 0.9867, "attributes": {"occluded": false, "rotation": 0.0}}, {"id": 26, "image_id": 3, "category_id": 9, "bbox": [388.14, 2556.87, 1939.43, 204.18], "area": 395994.74, "iscrowd": 0, "segmentation": [], "score": 0.9863, "attributes": {"occluded": false, "rotation": 0.0}}, {"id": 27, "image_id": 3, "category_id": 9, "bbox": [388.4, 2370.63, 1941.23, 152.4], "area": 295841.69, "iscrowd": 0, "segmentation": [], "score": 0.982, "attributes": {"occluded": false, "rotation": 0.0}}, {"id": 28, "image_id": 3, "category_id": 9, "bbox": [388.36, 1590.38, 1940.73, 156.25], "area": 303231.52, "iscrowd": 0, "segmentation": [], "score": 0.981, "attributes": {"occluded": false, "rotation": 0.0}}, {"id": 29, "image_id": 3, "category_id": 9, "bbox": [381.71, 458.97, 1944.71, 156.79], "area": 304916.89, "iscrowd": 0, "segmentation": [], "score": 0.9809, "attributes": {"occluded": false, "rotation": 0.0}}, {"id": 30, "image_id": 3, "category_id": 9, "bbox": [471.65, 1396.58, 1854.15, 156.94], "area": 290983.76, "iscrowd": 0, "segmentation": [], "score": 0.9759, "attributes": {"occluded": false, "rotation": 0.0}}, {"id": 31, "image_id": 3, "category_id": 9, "bbox": [387.8, 2818.57, 1938.48, 100.43], "area": 194690.31, "iscrowd": 0, "segmentation": [], "score": 0.9755, "attributes": {"occluded": false, "rotation": 0.0}}, {"id": 32, "image_id": 3, "category_id": 9, "bbox": [380.27, 651.4, 1944.82, 102.44], "area": 199230.27, "iscrowd": 0, "segmentation": [], "score": 0.973, "attributes": {"occluded": false, "rotation": 0.0}}, {"id": 33, "image_id": 3, "category_id": 9, "bbox": [380.55, 319.4, 1947.17, 102.41], "area": 199411.35, "iscrowd": 0, "segmentation": [], "score": 0.9722, "attributes": {"occluded": false, "rotation": 0.0}}, {"id": 34, "image_id": 3, "category_id": 9, "bbox": [387.9, 2034.56, 1185.39, 47.05], "area": 55771.27, "iscrowd": 0, "segmentation": [], "score": 0.9482, "attributes": {"occluded": false, "rotation": 0.0}}, {"id": 35, "image_id": 3, "category_id": 9, "bbox": [388.34, 874.25, 739.6, 47.01], "area": 34770.9, "iscrowd": 0, "segmentation": [], "score": 0.9377, "attributes": {"occluded": false, "rotation": 0.0}}, {"id": 36, "image_id": 3, "category_id": 9, "bbox": [387.3, 1867.34, 303.66, 46.49], "area": 14116.85, "iscrowd": 0, "segmentation": [], "score": 0.9367, "attributes": {"occluded": false, "rotation": 0.0}}, {"id": 37, "image_id": 3, "category_id": 9, "bbox": [387.06, 2203.16, 329.2, 45.68], "area": 15036.32, "iscrowd": 0, "segmentation": [], "score": 0.8954, "attributes": {"occluded": false, "rotation": 0.0}}, {"id": 38, "image_id": 3, "category_id": 17, "bbox": [1981.09, 3037.14, 316.03, 43.5], "area": 13746.83, "iscrowd": 0, "segmentation": [], "score": 0.9183, "attributes": {"occluded": false, "rotation": 0.0}}, {"id": 39, "image_id": 3, "category_id": 10, "bbox": [293.23, 2119.16, 815.49, 46.5], "area": 37917.04, "iscrowd": 0, "segmentation": [], "score": 0.9133, "attributes": {"occluded": false, "rotation": 0.0}}, {"id": 40, "image_id": 3, "category_id": 10, "bbox": [294.44, 789.21, 513.52, 48.52], "area": 24915.8, "iscrowd": 0, "segmentation": [], "score": 0.9096, "attributes": {"occluded": false, "rotation": 0.0}}, {"id": 41, "image_id": 3, "category_id": 10, "bbox": [294.58, 233.58, 358.69, 48.8], "area": 17503.15, "iscrowd": 0, "segmentation": [], "score": 0.9096, "attributes": {"occluded": false, "rotation": 0.0}}, {"id": 42, "image_id": 3, "category_id": 10, "bbox": [291.57, 2286.79, 1154.07, 47.78], "area": 55145.15, "iscrowd": 0, "segmentation": [], "score": 0.9044, "attributes": {"occluded": false, "rotation": 0.0}}, {"id": 43, "image_id": 3, "category_id": 10, "bbox": [293.75, 1951.34, 1292.79, 46.36], "area": 59928.98, "iscrowd": 0, "segmentation": [], "score": 0.9043, "attributes": {"occluded": false, "rotation": 0.0}}, {"id": 44, "image_id": 3, "category_id": 10, "bbox": [294.63, 956.31, 1562.54, 46.74], "area": 73031.14, "iscrowd": 0, "segmentation": [], "score": 0.9039, "attributes": {"occluded": false, "rotation": 0.0}}, {"id": 45, "image_id": 3, "category_id": 10, "bbox": [292.9, 1783.26, 1037.76, 46.83], "area": 48600.61, "iscrowd": 0, "segmentation": [], "score": 0.9011, "attributes": {"occluded": false, "rotation": 0.0}}, {"id": 46, "image_id": 4, "category_id": 8, "bbox": [379.36, 231.92, 1935.71, 2797.01], "area": 5414189.94, "iscrowd": 0, "segmentation": [], "score": 0.985, "attributes": {"occluded": false, "rotation": 0.0}}, {"id": 47, "image_id": 4, "category_id": 17, "bbox": [1983.2, 3040.07, 302.75, 39.48], "area": 11953.28, "iscrowd": 0, "segmentation": [], "score": 0.9322, "attributes": {"occluded": false, "rotation": 0.0}}, {"id": 48, "image_id": 5, "category_id": 8, "bbox": [379.56, 230.59, 1935.36, 2762.62], "area": 5346669.24, "iscrowd": 0, "segmentation": [], "score": 0.9871, "attributes": {"occluded": false, "rotation": 0.0}}, {"id": 49, "image_id": 5, "category_id": 17, "bbox": [1982.49, 3040.61, 303.78, 39.73], "area": 12067.67, "iscrowd": 0, "segmentation": [], "score": 0.9305, "attributes": {"occluded": false, "rotation": 0.0}}]}